{"reducedName":"alleghany,va","lowercaseName":"alleghany, va","areaname":"Alleghany, VA","stateCounty":51005,"totalPopulation":2015,"populationUnder18":3541,"populationOver65":19.4,"familiesBelowPovertyLevel":433,"medianFamilyIncome":52009,"meanFamilyIncome":58600,"incomeLessThan10K":195,"incomeBtw10And15K":211,"incomeBtw15And20K":259,"incomeBtw20And25K":182,"incomeBtw25And30K":474,"incomeBtw30And35K":225,"incomeBtw35And40K":252,"incomeBtw40And45K":325,"incomeBtw45And50K":282,"incomeBtw50And60K":475,"incomeBtw60And75K":809,"incomeBtw75And100K":692,"incomeBtw100And125K":348,"incomeBtw125And150K":177,"incomeBtw150And200K":95,"income200Plus":26,"unemploymentRate2009":9.2,"unemploymentRate2010":9,"percentageDem1980":50.7,"percentageDem1984":38.4,"percentageDem1988":47,"percentageDem1992":42.4,"percentageDem1996":47.3,"percentageDem2000":43.2,"percentageDem2004":44.5,"percentageDem2008":48.2,"percentageRep1980":45.9,"percentageRep1984":60.9,"percentageRep1988":51.9,"percentageRep1992":40.6,"percentageRep1996":39.7,"percentageRep2000":54.8,"percentageRep2004":55.1,"percentageRep2008":50.4,"whitePopulation":15056,"blackPopulation":916,"americanIndianAndAlaskanNativePopulation":31,"asianPopulation":66,"nativeHawaiianAndPacificIslanderPopulation":2,"twoOrMoreRacesPopulation":171,"hispanicOrLatinoPopulation":122,"normalizedName":"alleghany-va"}