{"reducedName":"chickasaw,ia","lowercaseName":"chickasaw, ia","areaname":"Chickasaw, IA","stateCounty":19037,"totalPopulation":2289,"populationUnder18":2935,"populationOver65":17.8,"familiesBelowPovertyLevel":166,"medianFamilyIncome":50837,"meanFamilyIncome":61193,"incomeLessThan10K":64,"incomeBtw10And15K":87,"incomeBtw15And20K":118,"incomeBtw20And25K":185,"incomeBtw25And30K":347,"incomeBtw30And35K":235,"incomeBtw35And40K":281,"incomeBtw40And45K":197,"incomeBtw45And50K":186,"incomeBtw50And60K":417,"incomeBtw60And75K":440,"incomeBtw75And100K":546,"incomeBtw100And125K":213,"incomeBtw125And150K":50,"incomeBtw150And200K":44,"income200Plus":59,"unemploymentRate2009":7.8,"unemploymentRate2010":7.3,"percentageDem1980":39.5,"percentageDem1984":46.1,"percentageDem1988":57.5,"percentageDem1992":43.9,"percentageDem1996":52.8,"percentageDem2000":52.2,"percentageDem2004":54.5,"percentageDem2008":59.6,"percentageRep1980":52.9,"percentageRep1984":52.9,"percentageRep1988":41.5,"percentageRep1992":32.1,"percentageRep1996":34.4,"percentageRep2000":44.6,"percentageRep2004":44.7,"percentageRep2008":38.8,"whitePopulation":11825,"blackPopulation":18,"americanIndianAndAlaskanNativePopulation":8,"asianPopulation":69,"nativeHawaiianAndPacificIslanderPopulation":5,"twoOrMoreRacesPopulation":92,"hispanicOrLatinoPopulation":179,"normalizedName":"chickasaw-ia"}