{"reducedName":"dakota,ne","lowercaseName":"dakota, ne","areaname":"Dakota, NE","stateCounty":31043,"totalPopulation":1783,"populationUnder18":6525,"populationOver65":9.1,"familiesBelowPovertyLevel":648,"medianFamilyIncome":52742,"meanFamilyIncome":58586,"incomeLessThan10K":294,"incomeBtw10And15K":190,"incomeBtw15And20K":144,"incomeBtw20And25K":313,"incomeBtw25And30K":340,"incomeBtw30And35K":358,"incomeBtw35And40K":335,"incomeBtw40And45K":302,"incomeBtw45And50K":281,"incomeBtw50And60K":759,"incomeBtw60And75K":759,"incomeBtw75And100K":721,"incomeBtw100And125K":320,"incomeBtw125And150K":129,"incomeBtw150And200K":173,"income200Plus":51,"unemploymentRate2009":6.2,"unemploymentRate2010":8,"percentageDem1980":35.2,"percentageDem1984":41.8,"percentageDem1988":51.6,"percentageDem1992":36.2,"percentageDem1996":44,"percentageDem2000":44.5,"percentageDem2004":45.8,"percentageDem2008":46.8,"percentageRep1980":57.7,"percentageRep1984":57.8,"percentageRep1988":48.2,"percentageRep1992":43.2,"percentageRep1996":43.3,"percentageRep2000":51.5,"percentageRep2004":53.3,"percentageRep2008":51.5,"whitePopulation":18428,"blackPopulation":549,"americanIndianAndAlaskanNativePopulation":593,"asianPopulation":769,"nativeHawaiianAndPacificIslanderPopulation":16,"twoOrMoreRacesPopulation":296,"hispanicOrLatinoPopulation":6657,"normalizedName":"dakota-ne"}