{"reducedName":"duchesne,ut","lowercaseName":"duchesne, ut","areaname":"Duchesne, UT","stateCounty":49013,"totalPopulation":1914,"populationUnder18":6288,"populationOver65":9.8,"familiesBelowPovertyLevel":394,"medianFamilyIncome":54880,"meanFamilyIncome":63920,"incomeLessThan10K":225,"incomeBtw10And15K":111,"incomeBtw15And20K":129,"incomeBtw20And25K":221,"incomeBtw25And30K":254,"incomeBtw30And35K":265,"incomeBtw35And40K":263,"incomeBtw40And45K":225,"incomeBtw45And50K":307,"incomeBtw50And60K":636,"incomeBtw60And75K":769,"incomeBtw75And100K":708,"incomeBtw100And125K":308,"incomeBtw125And150K":147,"incomeBtw150And200K":76,"income200Plus":112,"unemploymentRate2009":8.3,"unemploymentRate2010":8,"percentageDem1980":17.7,"percentageDem1984":14.3,"percentageDem1988":27.9,"percentageDem1992":16.9,"percentageDem1996":21.4,"percentageDem2000":17.1,"percentageDem2004":13.3,"percentageDem2008":15.9,"percentageRep1980":79.4,"percentageRep1984":85.2,"percentageRep1988":70.8,"percentageRep1992":43.4,"percentageRep1996":63.7,"percentageRep2000":79.7,"percentageRep2004":85.3,"percentageRep2008":81.6,"whitePopulation":16519,"blackPopulation":61,"americanIndianAndAlaskanNativePopulation":910,"asianPopulation":37,"nativeHawaiianAndPacificIslanderPopulation":10,"twoOrMoreRacesPopulation":411,"hispanicOrLatinoPopulation":985,"normalizedName":"duchesne-ut"}