{"reducedName":"eastcarroll,la","lowercaseName":"east carroll, la","areaname":"East Carroll, LA","stateCounty":22035,"totalPopulation":2579,"populationUnder18":2137,"populationOver65":13.1,"familiesBelowPovertyLevel":761,"medianFamilyIncome":23108,"meanFamilyIncome":51951,"incomeLessThan10K":314,"incomeBtw10And15K":436,"incomeBtw15And20K":156,"incomeBtw20And25K":233,"incomeBtw25And30K":149,"incomeBtw30And35K":67,"incomeBtw35And40K":66,"incomeBtw40And45K":135,"incomeBtw45And50K":9,"incomeBtw50And60K":290,"incomeBtw60And75K":61,"incomeBtw75And100K":62,"incomeBtw100And125K":101,"incomeBtw125And150K":32,"incomeBtw150And200K":0,"income200Plus":55,"unemploymentRate2009":12.6,"unemploymentRate2010":15.2,"percentageDem1980":54,"percentageDem1984":50.6,"percentageDem1988":52.3,"percentageDem1992":54.4,"percentageDem1996":63,"percentageDem2000":57.8,"percentageDem2004":58.3,"percentageDem2008":63.7,"percentageRep1980":44.1,"percentageRep1984":47.8,"percentageRep1988":44.4,"percentageRep1992":33.8,"percentageRep1996":29.6,"percentageRep2000":39.4,"percentageRep2004":40,"percentageRep2008":35.2,"whitePopulation":2546,"blackPopulation":5474,"americanIndianAndAlaskanNativePopulation":17,"asianPopulation":32,"nativeHawaiianAndPacificIslanderPopulation":0,"twoOrMoreRacesPopulation":33,"hispanicOrLatinoPopulation":134,"normalizedName":"eastcarroll-la"}