{"reducedName":"essex,vt","lowercaseName":"essex, vt","areaname":"Essex, VT","stateCounty":50009,"totalPopulation":2720,"populationUnder18":1184,"populationOver65":18.1,"familiesBelowPovertyLevel":215,"medianFamilyIncome":49093,"meanFamilyIncome":54646,"incomeLessThan10K":105,"incomeBtw10And15K":80,"incomeBtw15And20K":106,"incomeBtw20And25K":60,"incomeBtw25And30K":156,"incomeBtw30And35K":82,"incomeBtw35And40K":85,"incomeBtw40And45K":132,"incomeBtw45And50K":121,"incomeBtw50And60K":250,"incomeBtw60And75K":253,"incomeBtw75And100K":187,"incomeBtw100And125K":120,"incomeBtw125And150K":43,"incomeBtw150And200K":23,"income200Plus":14,"unemploymentRate2009":9.3,"unemploymentRate2010":9.1,"percentageDem1980":34.1,"percentageDem1984":29.5,"percentageDem1988":35,"percentageDem1992":36.4,"percentageDem1996":45.7,"percentageDem2000":39,"percentageDem2004":43.4,"percentageDem2008":55.9,"percentageRep1980":55.8,"percentageRep1984":69.5,"percentageRep1988":64.2,"percentageRep1992":34.6,"percentageRep1996":33.4,"percentageRep2000":54.1,"percentageRep2004":54.2,"percentageRep2008":41.4,"whitePopulation":6184,"blackPopulation":21,"americanIndianAndAlaskanNativePopulation":39,"asianPopulation":20,"nativeHawaiianAndPacificIslanderPopulation":0,"twoOrMoreRacesPopulation":130,"hispanicOrLatinoPopulation":46,"normalizedName":"essex-vt"}