{"reducedName":"frederick,va","lowercaseName":"frederick, va","areaname":"Frederick, VA","stateCounty":51069,"totalPopulation":718,"populationUnder18":19213,"populationOver65":11.4,"familiesBelowPovertyLevel":1229,"medianFamilyIncome":69387,"meanFamilyIncome":82278,"incomeLessThan10K":391,"incomeBtw10And15K":560,"incomeBtw15And20K":474,"incomeBtw20And25K":737,"incomeBtw25And30K":730,"incomeBtw30And35K":942,"incomeBtw35And40K":1056,"incomeBtw40And45K":970,"incomeBtw45And50K":898,"incomeBtw50And60K":1794,"incomeBtw60And75K":2290,"incomeBtw75And100K":3426,"incomeBtw100And125K":2663,"incomeBtw125And150K":1324,"incomeBtw150And200K":1089,"income200Plus":759,"unemploymentRate2009":7.7,"unemploymentRate2010":7,"percentageDem1980":27.3,"percentageDem1984":21.8,"percentageDem1988":27,"percentageDem1992":28.3,"percentageDem1996":32.5,"percentageDem2000":32,"percentageDem2004":31,"percentageDem2008":38.6,"percentageRep1980":67.6,"percentageRep1984":77.8,"percentageRep1988":72.3,"percentageRep1992":54,"percentageRep1996":57.6,"percentageRep2000":65.1,"percentageRep2004":67.9,"percentageRep2008":59.9,"whitePopulation":69354,"blackPopulation":3531,"americanIndianAndAlaskanNativePopulation":123,"asianPopulation":994,"nativeHawaiianAndPacificIslanderPopulation":18,"twoOrMoreRacesPopulation":952,"hispanicOrLatinoPopulation":4446,"normalizedName":"frederick-va"}