{"reducedName":"holmes,ms","lowercaseName":"holmes, ms","areaname":"Holmes, MS","stateCounty":28051,"totalPopulation":1802,"populationUnder18":6065,"populationOver65":12.1,"familiesBelowPovertyLevel":1774,"medianFamilyIncome":24529,"meanFamilyIncome":37038,"incomeLessThan10K":738,"incomeBtw10And15K":643,"incomeBtw15And20K":538,"incomeBtw20And25K":448,"incomeBtw25And30K":396,"incomeBtw30And35K":251,"incomeBtw35And40K":168,"incomeBtw40And45K":210,"incomeBtw45And50K":178,"incomeBtw50And60K":358,"incomeBtw60And75K":298,"incomeBtw75And100K":241,"incomeBtw100And125K":83,"incomeBtw125And150K":41,"incomeBtw150And200K":33,"income200Plus":38,"unemploymentRate2009":19.5,"unemploymentRate2010":19.5,"percentageDem1980":65.5,"percentageDem1984":64.4,"percentageDem1988":65.8,"percentageDem1992":68,"percentageDem1996":73.6,"percentageDem2000":73.4,"percentageDem2004":75.9,"percentageDem2008":81.4,"percentageRep1980":32.3,"percentageRep1984":35.4,"percentageRep1988":33.7,"percentageRep1992":28.2,"percentageRep1996":24,"percentageRep2000":26.1,"percentageRep2004":23.4,"percentageRep2008":18,"whitePopulation":3659,"blackPopulation":16411,"americanIndianAndAlaskanNativePopulation":35,"asianPopulation":43,"nativeHawaiianAndPacificIslanderPopulation":0,"twoOrMoreRacesPopulation":142,"hispanicOrLatinoPopulation":243,"normalizedName":"holmes-ms"}