{"reducedName":"jones,ms","lowercaseName":"jones, ms","areaname":"Jones, MS","stateCounty":28067,"totalPopulation":771,"populationUnder18":17487,"populationOver65":14.5,"familiesBelowPovertyLevel":3503,"medianFamilyIncome":39054,"meanFamilyIncome":53434,"incomeLessThan10K":1536,"incomeBtw10And15K":1204,"incomeBtw15And20K":1467,"incomeBtw20And25K":1472,"incomeBtw25And30K":1321,"incomeBtw30And35K":1196,"incomeBtw35And40K":1245,"incomeBtw40And45K":864,"incomeBtw45And50K":860,"incomeBtw50And60K":1794,"incomeBtw60And75K":1785,"incomeBtw75And100K":1707,"incomeBtw100And125K":656,"incomeBtw125And150K":585,"incomeBtw150And200K":284,"income200Plus":471,"unemploymentRate2009":7.6,"unemploymentRate2010":8.5,"percentageDem1980":45.8,"percentageDem1984":29.2,"percentageDem1988":30.4,"percentageDem1992":32.9,"percentageDem1996":33.7,"percentageDem2000":31.7,"percentageDem2004":27.7,"percentageDem2008":30.2,"percentageRep1980":53.1,"percentageRep1984":70.5,"percentageRep1988":69.1,"percentageRep1992":56.6,"percentageRep1996":59.6,"percentageRep2000":67.1,"percentageRep2004":71.7,"percentageRep2008":68.9,"whitePopulation":48093,"blackPopulation":18559,"americanIndianAndAlaskanNativePopulation":367,"asianPopulation":251,"nativeHawaiianAndPacificIslanderPopulation":14,"twoOrMoreRacesPopulation":492,"hispanicOrLatinoPopulation":3959,"normalizedName":"jones-ms"}