{"reducedName":"kent,tx","lowercaseName":"kent, tx","areaname":"Kent, TX","stateCounty":48263,"totalPopulation":3124,"populationUnder18":148,"populationOver65":25.9,"familiesBelowPovertyLevel":17,"medianFamilyIncome":43750,"meanFamilyIncome":52940,"incomeLessThan10K":17,"incomeBtw10And15K":0,"incomeBtw15And20K":13,"incomeBtw20And25K":5,"incomeBtw25And30K":7,"incomeBtw30And35K":26,"incomeBtw35And40K":24,"incomeBtw40And45K":4,"incomeBtw45And50K":6,"incomeBtw50And60K":19,"incomeBtw60And75K":34,"incomeBtw75And100K":16,"incomeBtw100And125K":12,"incomeBtw125And150K":3,"incomeBtw150And200K":6,"income200Plus":0,"unemploymentRate2009":5.2,"unemploymentRate2010":5.9,"percentageDem1980":50.6,"percentageDem1984":43,"percentageDem1988":59.1,"percentageDem1992":44.4,"percentageDem1996":50.5,"percentageDem2000":34.5,"percentageDem2004":26.4,"percentageDem2008":22.1,"percentageRep1980":48.8,"percentageRep1984":56.5,"percentageRep1988":40.7,"percentageRep1992":28.7,"percentageRep1996":36.3,"percentageRep2000":64.6,"percentageRep2004":73.2,"percentageRep2008":76.3,"whitePopulation":696,"blackPopulation":3,"americanIndianAndAlaskanNativePopulation":3,"asianPopulation":0,"nativeHawaiianAndPacificIslanderPopulation":0,"twoOrMoreRacesPopulation":1,"hispanicOrLatinoPopulation":115,"normalizedName":"kent-tx"}