{"reducedName":"kerr,tx","lowercaseName":"kerr, tx","areaname":"Kerr, TX","stateCounty":48265,"totalPopulation":987,"populationUnder18":10313,"populationOver65":25.4,"familiesBelowPovertyLevel":1299,"medianFamilyIncome":50697,"meanFamilyIncome":69082,"incomeLessThan10K":507,"incomeBtw10And15K":475,"incomeBtw15And20K":697,"incomeBtw20And25K":700,"incomeBtw25And30K":764,"incomeBtw30And35K":1016,"incomeBtw35And40K":1082,"incomeBtw40And45K":758,"incomeBtw45And50K":703,"incomeBtw50And60K":1144,"incomeBtw60And75K":1428,"incomeBtw75And100K":1930,"incomeBtw100And125K":724,"incomeBtw125And150K":602,"incomeBtw150And200K":498,"income200Plus":512,"unemploymentRate2009":5.8,"unemploymentRate2010":6.2,"percentageDem1980":26.3,"percentageDem1984":20.7,"percentageDem1988":24,"percentageDem1992":22.7,"percentageDem1996":25,"percentageDem2000":20.8,"percentageDem2004":21.4,"percentageDem2008":24.7,"percentageRep1980":70.7,"percentageRep1984":79,"percentageRep1988":75,"percentageRep1992":53.7,"percentageRep1996":66.6,"percentageRep2000":76.1,"percentageRep2004":77.8,"percentageRep2008":74.3,"whitePopulation":46216,"blackPopulation":1001,"americanIndianAndAlaskanNativePopulation":315,"asianPopulation":303,"nativeHawaiianAndPacificIslanderPopulation":23,"twoOrMoreRacesPopulation":523,"hispanicOrLatinoPopulation":11293,"normalizedName":"kerr-tx"}