{"reducedName":"knott,ky","lowercaseName":"knott, ky","areaname":"Knott, KY","stateCounty":21119,"totalPopulation":1956,"populationUnder18":3531,"populationOver65":12.7,"familiesBelowPovertyLevel":1060,"medianFamilyIncome":35630,"meanFamilyIncome":45167,"incomeLessThan10K":490,"incomeBtw10And15K":463,"incomeBtw15And20K":410,"incomeBtw20And25K":331,"incomeBtw25And30K":317,"incomeBtw30And35K":296,"incomeBtw35And40K":231,"incomeBtw40And45K":176,"incomeBtw45And50K":191,"incomeBtw50And60K":511,"incomeBtw60And75K":463,"incomeBtw75And100K":432,"incomeBtw100And125K":187,"incomeBtw125And150K":123,"incomeBtw150And200K":49,"income200Plus":12,"unemploymentRate2009":10.9,"unemploymentRate2010":13.4,"percentageDem1980":76.5,"percentageDem1984":71.8,"percentageDem1988":74.9,"percentageDem1992":75.1,"percentageDem1996":73.3,"percentageDem2000":67.3,"percentageDem2004":63.4,"percentageDem2008":44.9,"percentageRep1980":22.7,"percentageRep1984":27.7,"percentageRep1988":24.4,"percentageRep1992":17,"percentageRep1996":18.2,"percentageRep2000":31.4,"percentageRep2004":35.8,"percentageRep2008":52.7,"whitePopulation":16803,"blackPopulation":153,"americanIndianAndAlaskanNativePopulation":21,"asianPopulation":28,"nativeHawaiianAndPacificIslanderPopulation":1,"twoOrMoreRacesPopulation":120,"hispanicOrLatinoPopulation":151,"normalizedName":"knott-ky"}