{"reducedName":"lawrence,ky","lowercaseName":"lawrence, ky","areaname":"Lawrence, KY","stateCounty":21127,"totalPopulation":1991,"populationUnder18":3882,"populationOver65":13.5,"familiesBelowPovertyLevel":1067,"medianFamilyIncome":31358,"meanFamilyIncome":41940,"incomeLessThan10K":417,"incomeBtw10And15K":438,"incomeBtw15And20K":508,"incomeBtw20And25K":394,"incomeBtw25And30K":294,"incomeBtw30And35K":270,"incomeBtw35And40K":402,"incomeBtw40And45K":231,"incomeBtw45And50K":164,"incomeBtw50And60K":239,"incomeBtw60And75K":254,"incomeBtw75And100K":341,"incomeBtw100And125K":190,"incomeBtw125And150K":111,"incomeBtw150And200K":13,"income200Plus":24,"unemploymentRate2009":12.2,"unemploymentRate2010":12.8,"percentageDem1980":47.4,"percentageDem1984":44.8,"percentageDem1988":48.8,"percentageDem1992":47.5,"percentageDem1996":48.7,"percentageDem2000":42.5,"percentageDem2004":41.5,"percentageDem2008":36,"percentageRep1980":51.5,"percentageRep1984":54.7,"percentageRep1988":50.9,"percentageRep1992":41.2,"percentageRep1996":40.2,"percentageRep2000":55.9,"percentageRep2004":57.7,"percentageRep2008":62,"whitePopulation":16331,"blackPopulation":73,"americanIndianAndAlaskanNativePopulation":48,"asianPopulation":13,"nativeHawaiianAndPacificIslanderPopulation":1,"twoOrMoreRacesPopulation":107,"hispanicOrLatinoPopulation":84,"normalizedName":"lawrence-ky"}