{"reducedName":"leon,fl","lowercaseName":"leon, fl","areaname":"Leon, FL","stateCounty":12073,"totalPopulation":243,"populationUnder18":52091,"populationOver65":9.2,"familiesBelowPovertyLevel":6540,"medianFamilyIncome":64987,"meanFamilyIncome":81769,"incomeLessThan10K":3907,"incomeBtw10And15K":1965,"incomeBtw15And20K":1921,"incomeBtw20And25K":2540,"incomeBtw25And30K":2121,"incomeBtw30And35K":2426,"incomeBtw35And40K":3188,"incomeBtw40And45K":2160,"incomeBtw45And50K":2346,"incomeBtw50And60K":4536,"incomeBtw60And75K":6466,"incomeBtw75And100K":9047,"incomeBtw100And125K":5973,"incomeBtw125And150K":3896,"incomeBtw150And200K":3523,"income200Plus":2861,"unemploymentRate2009":6.8,"unemploymentRate2010":8.2,"percentageDem1980":49.6,"percentageDem1984":44.9,"percentageDem1988":47.7,"percentageDem1992":49.1,"percentageDem1996":54.6,"percentageDem2000":59.6,"percentageDem2004":61.5,"percentageDem2008":61.7,"percentageRep1980":43.5,"percentageRep1984":55,"percentageRep1988":51.4,"percentageRep1992":32.9,"percentageRep1996":37,"percentageRep2000":37.9,"percentageRep2004":37.8,"percentageRep2008":37.5,"whitePopulation":168759,"blackPopulation":84979,"americanIndianAndAlaskanNativePopulation":871,"asianPopulation":6854,"nativeHawaiianAndPacificIslanderPopulation":151,"twoOrMoreRacesPopulation":4100,"hispanicOrLatinoPopulation":12503,"normalizedName":"leon-fl"}