{"reducedName":"luna,nm","lowercaseName":"luna, nm","areaname":"Luna, NM","stateCounty":35029,"totalPopulation":1517,"populationUnder18":7473,"populationOver65":19.8,"familiesBelowPovertyLevel":1807,"medianFamilyIncome":32357,"meanFamilyIncome":43554,"incomeLessThan10K":834,"incomeBtw10And15K":501,"incomeBtw15And20K":620,"incomeBtw20And25K":487,"incomeBtw25And30K":528,"incomeBtw30And35K":578,"incomeBtw35And40K":467,"incomeBtw40And45K":391,"incomeBtw45And50K":213,"incomeBtw50And60K":489,"incomeBtw60And75K":553,"incomeBtw75And100K":414,"incomeBtw100And125K":167,"incomeBtw125And150K":50,"incomeBtw150And200K":38,"income200Plus":106,"unemploymentRate2009":16.4,"unemploymentRate2010":18.7,"percentageDem1980":38.3,"percentageDem1984":37.7,"percentageDem1988":46.2,"percentageDem1992":42,"percentageDem1996":47.4,"percentageDem2000":45,"percentageDem2004":44,"percentageDem2008":51.7,"percentageRep1980":57.1,"percentageRep1984":61.2,"percentageRep1988":51.5,"percentageRep1992":34.5,"percentageRep1996":41.4,"percentageRep2000":51.3,"percentageRep2004":54.8,"percentageRep2008":46.4,"whitePopulation":25693,"blackPopulation":506,"americanIndianAndAlaskanNativePopulation":386,"asianPopulation":151,"nativeHawaiianAndPacificIslanderPopulation":3,"twoOrMoreRacesPopulation":305,"hispanicOrLatinoPopulation":16592,"normalizedName":"luna-nm"}