{"reducedName":"martin,tx","lowercaseName":"martin, tx","areaname":"Martin, TX","stateCounty":48317,"totalPopulation":2856,"populationUnder18":1421,"populationOver65":12.4,"familiesBelowPovertyLevel":66,"medianFamilyIncome":47712,"meanFamilyIncome":63496,"incomeLessThan10K":16,"incomeBtw10And15K":33,"incomeBtw15And20K":109,"incomeBtw20And25K":107,"incomeBtw25And30K":25,"incomeBtw30And35K":237,"incomeBtw35And40K":75,"incomeBtw40And45K":74,"incomeBtw45And50K":93,"incomeBtw50And60K":51,"incomeBtw60And75K":261,"incomeBtw75And100K":77,"incomeBtw100And125K":93,"incomeBtw125And150K":60,"incomeBtw150And200K":89,"income200Plus":19,"unemploymentRate2009":4.8,"unemploymentRate2010":5.7,"percentageDem1980":35.3,"percentageDem1984":29.4,"percentageDem1988":38.3,"percentageDem1992":32.2,"percentageDem1996":36.3,"percentageDem2000":21.3,"percentageDem2004":15.9,"percentageDem2008":18.3,"percentageRep1980":63.7,"percentageRep1984":70,"percentageRep1988":61.6,"percentageRep1992":49.6,"percentageRep1996":54.9,"percentageRep2000":78,"percentageRep2004":83.8,"percentageRep2008":81,"whitePopulation":4382,"blackPopulation":92,"americanIndianAndAlaskanNativePopulation":54,"asianPopulation":9,"nativeHawaiianAndPacificIslanderPopulation":0,"twoOrMoreRacesPopulation":44,"hispanicOrLatinoPopulation":2041,"normalizedName":"martin-tx"}