{"reducedName":"mecosta,mi","lowercaseName":"mecosta, mi","areaname":"Mecosta, MI","stateCounty":26107,"totalPopulation":1119,"populationUnder18":8194,"populationOver65":15.9,"familiesBelowPovertyLevel":1161,"medianFamilyIncome":49334,"meanFamilyIncome":58050,"incomeLessThan10K":551,"incomeBtw10And15K":358,"incomeBtw15And20K":595,"incomeBtw20And25K":490,"incomeBtw25And30K":668,"incomeBtw30And35K":682,"incomeBtw35And40K":662,"incomeBtw40And45K":567,"incomeBtw45And50K":492,"incomeBtw50And60K":1194,"incomeBtw60And75K":1115,"incomeBtw75And100K":1243,"incomeBtw100And125K":662,"incomeBtw125And150K":407,"incomeBtw150And200K":192,"income200Plus":113,"unemploymentRate2009":12.5,"unemploymentRate2010":12.1,"percentageDem1980":36,"percentageDem1984":30.8,"percentageDem1988":36.5,"percentageDem1992":38.5,"percentageDem1996":48.5,"percentageDem2000":42.7,"percentageDem2004":44,"percentageDem2008":48.8,"percentageRep1980":53.4,"percentageRep1984":68.7,"percentageRep1988":63,"percentageRep1992":38.2,"percentageRep1996":40.3,"percentageRep2000":54.7,"percentageRep2004":55.2,"percentageRep2008":49.5,"whitePopulation":38564,"blackPopulation":1705,"americanIndianAndAlaskanNativePopulation":306,"asianPopulation":450,"nativeHawaiianAndPacificIslanderPopulation":17,"twoOrMoreRacesPopulation":733,"hispanicOrLatinoPopulation":636,"normalizedName":"mecosta-mi"}