{"reducedName":"mitchell,tx","lowercaseName":"mitchell, tx","areaname":"Mitchell, TX","stateCounty":48335,"totalPopulation":2472,"populationUnder18":1818,"populationOver65":12.3,"familiesBelowPovertyLevel":223,"medianFamilyIncome":50310,"meanFamilyIncome":57410,"incomeLessThan10K":89,"incomeBtw10And15K":17,"incomeBtw15And20K":97,"incomeBtw20And25K":157,"incomeBtw25And30K":85,"incomeBtw30And35K":173,"incomeBtw35And40K":114,"incomeBtw40And45K":180,"incomeBtw45And50K":131,"incomeBtw50And60K":326,"incomeBtw60And75K":228,"incomeBtw75And100K":303,"incomeBtw100And125K":153,"incomeBtw125And150K":14,"incomeBtw150And200K":47,"income200Plus":10,"unemploymentRate2009":8.3,"unemploymentRate2010":8.6,"percentageDem1980":49.4,"percentageDem1984":39.7,"percentageDem1988":52.5,"percentageDem1992":43.7,"percentageDem1996":50.4,"percentageDem2000":32.5,"percentageDem2004":25,"percentageDem2008":24.1,"percentageRep1980":49.7,"percentageRep1984":59.8,"percentageRep1988":47.3,"percentageRep1992":36.5,"percentageRep1996":39.5,"percentageRep2000":66.4,"percentageRep2004":74.7,"percentageRep2008":74.7,"whitePopulation":7821,"blackPopulation":1348,"americanIndianAndAlaskanNativePopulation":70,"asianPopulation":42,"nativeHawaiianAndPacificIslanderPopulation":2,"twoOrMoreRacesPopulation":64,"hispanicOrLatinoPopulation":3112,"normalizedName":"mitchell-tx"}