{"reducedName":"mower,mn","lowercaseName":"mower, mn","areaname":"Mower, MN","stateCounty":27099,"totalPopulation":1207,"populationUnder18":9621,"populationOver65":18.4,"familiesBelowPovertyLevel":1052,"medianFamilyIncome":56379,"meanFamilyIncome":66611,"incomeLessThan10K":609,"incomeBtw10And15K":241,"incomeBtw15And20K":417,"incomeBtw20And25K":555,"incomeBtw25And30K":458,"incomeBtw30And35K":448,"incomeBtw35And40K":575,"incomeBtw40And45K":630,"incomeBtw45And50K":633,"incomeBtw50And60K":1024,"incomeBtw60And75K":1409,"incomeBtw75And100K":1617,"incomeBtw100And125K":928,"incomeBtw125And150K":365,"incomeBtw150And200K":288,"income200Plus":241,"unemploymentRate2009":6.5,"unemploymentRate2010":5.9,"percentageDem1980":51.8,"percentageDem1984":60.5,"percentageDem1988":62.4,"percentageDem1992":49.2,"percentageDem1996":57.6,"percentageDem2000":57.9,"percentageDem2004":61,"percentageDem2008":60.5,"percentageRep1980":38.9,"percentageRep1984":39,"percentageRep1988":36.6,"percentageRep1992":25.5,"percentageRep1996":27.6,"percentageRep2000":37.2,"percentageRep2004":37.5,"percentageRep2008":36.9,"whitePopulation":36333,"blackPopulation":632,"americanIndianAndAlaskanNativePopulation":131,"asianPopulation":762,"nativeHawaiianAndPacificIslanderPopulation":6,"twoOrMoreRacesPopulation":351,"hispanicOrLatinoPopulation":3480,"normalizedName":"mower-mn"}