{"reducedName":"pope,ar","lowercaseName":"pope, ar","areaname":"Pope, AR","stateCounty":5115,"totalPopulation":846,"populationUnder18":14186,"populationOver65":14.2,"familiesBelowPovertyLevel":1925,"medianFamilyIncome":46224,"meanFamilyIncome":57949,"incomeLessThan10K":812,"incomeBtw10And15K":602,"incomeBtw15And20K":1070,"incomeBtw20And25K":1048,"incomeBtw25And30K":916,"incomeBtw30And35K":1019,"incomeBtw35And40K":900,"incomeBtw40And45K":902,"incomeBtw45And50K":962,"incomeBtw50And60K":1373,"incomeBtw60And75K":1634,"incomeBtw75And100K":1684,"incomeBtw100And125K":1059,"incomeBtw125And150K":369,"incomeBtw150And200K":486,"income200Plus":224,"unemploymentRate2009":7.1,"unemploymentRate2010":7.7,"percentageDem1980":44.7,"percentageDem1984":32.1,"percentageDem1988":32.7,"percentageDem1992":43.1,"percentageDem1996":44.8,"percentageDem2000":36.2,"percentageDem2004":34,"percentageDem2008":27.2,"percentageRep1980":50.7,"percentageRep1984":67.3,"percentageRep1988":66.7,"percentageRep1992":45.1,"percentageRep1996":43.8,"percentageRep2000":61,"percentageRep2004":65.1,"percentageRep2008":70.5,"whitePopulation":56320,"blackPopulation":2059,"americanIndianAndAlaskanNativePopulation":413,"asianPopulation":545,"nativeHawaiianAndPacificIslanderPopulation":14,"twoOrMoreRacesPopulation":863,"hispanicOrLatinoPopulation":3143,"normalizedName":"pope-ar"}