{"reducedName":"pottawatomie,ok","lowercaseName":"pottawatomie, ok","areaname":"Pottawatomie, OK","stateCounty":40125,"totalPopulation":752,"populationUnder18":17269,"populationOver65":14.4,"familiesBelowPovertyLevel":2470,"medianFamilyIncome":47527,"meanFamilyIncome":57581,"incomeLessThan10K":1248,"incomeBtw10And15K":730,"incomeBtw15And20K":1016,"incomeBtw20And25K":1085,"incomeBtw25And30K":1292,"incomeBtw30And35K":1036,"incomeBtw35And40K":1068,"incomeBtw40And45K":959,"incomeBtw45And50K":998,"incomeBtw50And60K":1759,"incomeBtw60And75K":2186,"incomeBtw75And100K":2078,"incomeBtw100And125K":1204,"incomeBtw125And150K":586,"incomeBtw150And200K":258,"income200Plus":251,"unemploymentRate2009":6.5,"unemploymentRate2010":6.7,"percentageDem1980":39,"percentageDem1984":29.9,"percentageDem1988":41.9,"percentageDem1992":33.7,"percentageDem1996":42,"percentageDem2000":39.3,"percentageDem2004":33.4,"percentageDem2008":30.8,"percentageRep1980":57.1,"percentageRep1984":69.4,"percentageRep1988":57.2,"percentageRep1992":40.5,"percentageRep1996":45.1,"percentageRep2000":59.3,"percentageRep2004":66.6,"percentageRep2008":69.2,"whitePopulation":55327,"blackPopulation":2412,"americanIndianAndAlaskanNativePopulation":8410,"asianPopulation":501,"nativeHawaiianAndPacificIslanderPopulation":104,"twoOrMoreRacesPopulation":3520,"hispanicOrLatinoPopulation":2560,"normalizedName":"pottawatomie-ok"}