{"reducedName":"putnam,il","lowercaseName":"putnam, il","areaname":"Putnam, IL","stateCounty":17155,"totalPopulation":2758,"populationUnder18":1324,"populationOver65":17.7,"familiesBelowPovertyLevel":111,"medianFamilyIncome":66602,"meanFamilyIncome":72601,"incomeLessThan10K":44,"incomeBtw10And15K":57,"incomeBtw15And20K":23,"incomeBtw20And25K":79,"incomeBtw25And30K":31,"incomeBtw30And35K":75,"incomeBtw35And40K":106,"incomeBtw40And45K":40,"incomeBtw45And50K":92,"incomeBtw50And60K":196,"incomeBtw60And75K":217,"incomeBtw75And100K":341,"incomeBtw100And125K":257,"incomeBtw125And150K":71,"incomeBtw150And200K":46,"income200Plus":22,"unemploymentRate2009":13.4,"unemploymentRate2010":12,"percentageDem1980":33.9,"percentageDem1984":43.6,"percentageDem1988":51,"percentageDem1992":47.6,"percentageDem1996":51.6,"percentageDem2000":52.1,"percentageDem2004":50.8,"percentageDem2008":56.9,"percentageRep1980":57.4,"percentageRep1984":56,"percentageRep1988":48.3,"percentageRep1992":29.3,"percentageRep1996":35.7,"percentageRep2000":45.2,"percentageRep2004":48.4,"percentageRep2008":41.3,"whitePopulation":5884,"blackPopulation":47,"americanIndianAndAlaskanNativePopulation":26,"asianPopulation":20,"nativeHawaiianAndPacificIslanderPopulation":0,"twoOrMoreRacesPopulation":32,"hispanicOrLatinoPopulation":280,"normalizedName":"putnam-il"}