{"reducedName":"ravalli,mt","lowercaseName":"ravalli, mt","areaname":"Ravalli, MT","stateCounty":30081,"totalPopulation":1165,"populationUnder18":8858,"populationOver65":18.5,"familiesBelowPovertyLevel":857,"medianFamilyIncome":53342,"meanFamilyIncome":66973,"incomeLessThan10K":351,"incomeBtw10And15K":386,"incomeBtw15And20K":389,"incomeBtw20And25K":700,"incomeBtw25And30K":521,"incomeBtw30And35K":552,"incomeBtw35And40K":626,"incomeBtw40And45K":623,"incomeBtw45And50K":559,"incomeBtw50And60K":953,"incomeBtw60And75K":1221,"incomeBtw75And100K":1422,"incomeBtw100And125K":684,"incomeBtw125And150K":215,"incomeBtw150And200K":371,"income200Plus":325,"unemploymentRate2009":8.5,"unemploymentRate2010":9.7,"percentageDem1980":26.9,"percentageDem1984":31.5,"percentageDem1988":38.1,"percentageDem1992":30.9,"percentageDem1996":32,"percentageDem2000":25.8,"percentageDem2004":30.9,"percentageDem2008":38,"percentageRep1980":63.7,"percentageRep1984":67.1,"percentageRep1988":59.4,"percentageRep1992":35.9,"percentageRep1996":50.1,"percentageRep2000":65.2,"percentageRep2004":66.8,"percentageRep2008":58.8,"whitePopulation":39251,"blackPopulation":105,"americanIndianAndAlaskanNativePopulation":379,"asianPopulation":145,"nativeHawaiianAndPacificIslanderPopulation":34,"twoOrMoreRacesPopulation":517,"hispanicOrLatinoPopulation":1131,"normalizedName":"ravalli-mt"}