{"reducedName":"saratoga,ny","lowercaseName":"saratoga, ny","areaname":"Saratoga, NY","stateCounty":36091,"totalPopulation":285,"populationUnder18":48324,"populationOver65":13.1,"familiesBelowPovertyLevel":2329,"medianFamilyIncome":80132,"meanFamilyIncome":92920,"incomeLessThan10K":1185,"incomeBtw10And15K":972,"incomeBtw15And20K":1144,"incomeBtw20And25K":1493,"incomeBtw25And30K":1778,"incomeBtw30And35K":1876,"incomeBtw35And40K":2027,"incomeBtw40And45K":2038,"incomeBtw45And50K":2266,"incomeBtw50And60K":4507,"incomeBtw60And75K":6910,"incomeBtw75And100K":11006,"incomeBtw100And125K":7673,"incomeBtw125And150K":4572,"incomeBtw150And200K":4357,"income200Plus":3109,"unemploymentRate2009":6.5,"unemploymentRate2010":6.8,"percentageDem1980":36.2,"percentageDem1984":31.8,"percentageDem1988":41.8,"percentageDem1992":36.8,"percentageDem1996":46.5,"percentageDem2000":45.6,"percentageDem2004":45.6,"percentageDem2008":50.9,"percentageRep1980":52.3,"percentageRep1984":67.9,"percentageRep1988":57.4,"percentageRep1992":41.1,"percentageRep1996":40.1,"percentageRep2000":49,"percentageRep2004":52.5,"percentageRep2008":47.5,"whitePopulation":209310,"blackPopulation":3883,"americanIndianAndAlaskanNativePopulation":464,"asianPopulation":3833,"nativeHawaiianAndPacificIslanderPopulation":54,"twoOrMoreRacesPopulation":2525,"hispanicOrLatinoPopulation":4866,"normalizedName":"saratoga-ny"}