{"reducedName":"shackelford,tx","lowercaseName":"shackelford, tx","areaname":"Shackelford, TX","stateCounty":48417,"totalPopulation":2965,"populationUnder18":720,"populationOver65":18.3,"familiesBelowPovertyLevel":81,"medianFamilyIncome":51343,"meanFamilyIncome":59153,"incomeLessThan10K":53,"incomeBtw10And15K":15,"incomeBtw15And20K":46,"incomeBtw20And25K":36,"incomeBtw25And30K":48,"incomeBtw30And35K":64,"incomeBtw35And40K":24,"incomeBtw40And45K":54,"incomeBtw45And50K":49,"incomeBtw50And60K":86,"incomeBtw60And75K":115,"incomeBtw75And100K":103,"incomeBtw100And125K":35,"incomeBtw125And150K":56,"incomeBtw150And200K":19,"income200Plus":4,"unemploymentRate2009":4,"unemploymentRate2010":4.6,"percentageDem1980":38.3,"percentageDem1984":25.9,"percentageDem1988":43.8,"percentageDem1992":31.6,"percentageDem1996":34.1,"percentageDem2000":19.6,"percentageDem2004":15,"percentageDem2008":13.8,"percentageRep1980":60.7,"percentageRep1984":73.6,"percentageRep1988":55.7,"percentageRep1992":40.6,"percentageRep1996":53.8,"percentageRep2000":79.1,"percentageRep2004":84.6,"percentageRep2008":85.3,"whitePopulation":2978,"blackPopulation":30,"americanIndianAndAlaskanNativePopulation":17,"asianPopulation":0,"nativeHawaiianAndPacificIslanderPopulation":0,"twoOrMoreRacesPopulation":22,"hispanicOrLatinoPopulation":377,"normalizedName":"shackelford-tx"}