{"reducedName":"skamania,wa","lowercaseName":"skamania, wa","areaname":"Skamania, WA","stateCounty":53059,"totalPopulation":2359,"populationUnder18":2438,"populationOver65":13,"familiesBelowPovertyLevel":147,"medianFamilyIncome":55339,"meanFamilyIncome":66755,"incomeLessThan10K":81,"incomeBtw10And15K":115,"incomeBtw15And20K":88,"incomeBtw20And25K":100,"incomeBtw25And30K":241,"incomeBtw30And35K":144,"incomeBtw35And40K":139,"incomeBtw40And45K":194,"incomeBtw45And50K":189,"incomeBtw50And60K":321,"incomeBtw60And75K":438,"incomeBtw75And100K":432,"incomeBtw100And125K":220,"incomeBtw125And150K":138,"incomeBtw150And200K":76,"income200Plus":35,"unemploymentRate2009":13,"unemploymentRate2010":13.2,"percentageDem1980":44.4,"percentageDem1984":46.5,"percentageDem1988":55.3,"percentageDem1992":40.1,"percentageDem1996":45.5,"percentageDem2000":41.3,"percentageDem2004":46,"percentageDem2008":51.3,"percentageRep1980":45.8,"percentageRep1984":52,"percentageRep1988":42.9,"percentageRep1992":29.9,"percentageRep1996":36.6,"percentageRep2000":50.6,"percentageRep2004":52.2,"percentageRep2008":46,"whitePopulation":10282,"blackPopulation":38,"americanIndianAndAlaskanNativePopulation":264,"asianPopulation":63,"nativeHawaiianAndPacificIslanderPopulation":17,"twoOrMoreRacesPopulation":230,"hispanicOrLatinoPopulation":649,"normalizedName":"skamania-wa"}