{"reducedName":"stoddard,mo","lowercaseName":"stoddard, mo","areaname":"Stoddard, MO","stateCounty":29207,"totalPopulation":1451,"populationUnder18":6755,"populationOver65":17.6,"familiesBelowPovertyLevel":1039,"medianFamilyIncome":43770,"meanFamilyIncome":54905,"incomeLessThan10K":330,"incomeBtw10And15K":464,"incomeBtw15And20K":725,"incomeBtw20And25K":545,"incomeBtw25And30K":661,"incomeBtw30And35K":488,"incomeBtw35And40K":592,"incomeBtw40And45K":447,"incomeBtw45And50K":408,"incomeBtw50And60K":891,"incomeBtw60And75K":978,"incomeBtw75And100K":893,"incomeBtw100And125K":388,"incomeBtw125And150K":281,"incomeBtw150And200K":116,"income200Plus":117,"unemploymentRate2009":9.5,"unemploymentRate2010":9.1,"percentageDem1980":44.5,"percentageDem1984":39.1,"percentageDem1988":44.6,"percentageDem1992":46.5,"percentageDem1996":43.7,"percentageDem2000":35.9,"percentageDem2004":29.8,"percentageDem2008":29.4,"percentageRep1980":53.8,"percentageRep1984":60.9,"percentageRep1988":55.2,"percentageRep1992":37.4,"percentageRep1996":44.9,"percentageRep2000":62,"percentageRep2004":69.7,"percentageRep2008":69.2,"whitePopulation":28094,"blackPopulation":421,"americanIndianAndAlaskanNativePopulation":131,"asianPopulation":84,"nativeHawaiianAndPacificIslanderPopulation":6,"twoOrMoreRacesPopulation":333,"hispanicOrLatinoPopulation":346,"normalizedName":"stoddard-mo"}