{"reducedName":"terry,tx","lowercaseName":"terry, tx","areaname":"Terry, TX","stateCounty":48445,"totalPopulation":2281,"populationUnder18":3269,"populationOver65":14.1,"familiesBelowPovertyLevel":434,"medianFamilyIncome":42870,"meanFamilyIncome":68255,"incomeLessThan10K":247,"incomeBtw10And15K":69,"incomeBtw15And20K":181,"incomeBtw20And25K":124,"incomeBtw25And30K":174,"incomeBtw30And35K":241,"incomeBtw35And40K":372,"incomeBtw40And45K":132,"incomeBtw45And50K":146,"incomeBtw50And60K":310,"incomeBtw60And75K":205,"incomeBtw75And100K":228,"incomeBtw100And125K":196,"incomeBtw125And150K":111,"incomeBtw150And200K":71,"income200Plus":106,"unemploymentRate2009":6.9,"unemploymentRate2010":7.4,"percentageDem1980":37.4,"percentageDem1984":32.5,"percentageDem1988":42.2,"percentageDem1992":33.2,"percentageDem1996":35.7,"percentageDem2000":27.3,"percentageDem2004":20,"percentageDem2008":32.2,"percentageRep1980":61.2,"percentageRep1984":67.3,"percentageRep1988":57.5,"percentageRep1992":52.5,"percentageRep1996":56.4,"percentageRep2000":71.8,"percentageRep2004":79.7,"percentageRep2008":67.3,"whitePopulation":11200,"blackPopulation":708,"americanIndianAndAlaskanNativePopulation":94,"asianPopulation":42,"nativeHawaiianAndPacificIslanderPopulation":3,"twoOrMoreRacesPopulation":95,"hispanicOrLatinoPopulation":5974,"normalizedName":"terry-tx"}