{"reducedName":"todd,ky","lowercaseName":"todd, ky","areaname":"Todd, KY","stateCounty":21219,"totalPopulation":2276,"populationUnder18":3343,"populationOver65":13.5,"familiesBelowPovertyLevel":396,"medianFamilyIncome":45429,"meanFamilyIncome":55085,"incomeLessThan10K":182,"incomeBtw10And15K":155,"incomeBtw15And20K":170,"incomeBtw20And25K":227,"incomeBtw25And30K":230,"incomeBtw30And35K":229,"incomeBtw35And40K":230,"incomeBtw40And45K":276,"incomeBtw45And50K":215,"incomeBtw50And60K":417,"incomeBtw60And75K":349,"incomeBtw75And100K":428,"incomeBtw100And125K":147,"incomeBtw125And150K":71,"incomeBtw150And200K":70,"income200Plus":48,"unemploymentRate2009":12.3,"unemploymentRate2010":10.7,"percentageDem1980":49.1,"percentageDem1984":35.2,"percentageDem1988":41.2,"percentageDem1992":44.2,"percentageDem1996":42.4,"percentageDem2000":35.7,"percentageDem2004":31.4,"percentageDem2008":31.2,"percentageRep1980":48.9,"percentageRep1984":55.2,"percentageRep1988":57.7,"percentageRep1992":40.2,"percentageRep1996":46.4,"percentageRep2000":63.2,"percentageRep2004":68.2,"percentageRep2008":67.5,"whitePopulation":11039,"blackPopulation":1080,"americanIndianAndAlaskanNativePopulation":22,"asianPopulation":23,"nativeHawaiianAndPacificIslanderPopulation":4,"twoOrMoreRacesPopulation":85,"hispanicOrLatinoPopulation":375,"normalizedName":"todd-ky"}