{"reducedName":"utah,ut","lowercaseName":"utah, ut","areaname":"Utah, UT","stateCounty":49049,"totalPopulation":112,"populationUnder18":189454,"populationOver65":6.5,"familiesBelowPovertyLevel":8283,"medianFamilyIncome":63310,"meanFamilyIncome":77549,"incomeLessThan10K":3291,"incomeBtw10And15K":2897,"incomeBtw15And20K":3262,"incomeBtw20And25K":4123,"incomeBtw25And30K":4582,"incomeBtw30And35K":5077,"incomeBtw35And40K":5405,"incomeBtw40And45K":5137,"incomeBtw45And50K":5062,"incomeBtw50And60K":10005,"incomeBtw60And75K":14486,"incomeBtw75And100K":17258,"incomeBtw100And125K":10386,"incomeBtw125And150K":5269,"incomeBtw150And200K":4571,"income200Plus":3665,"unemploymentRate2009":6.8,"unemploymentRate2010":7.7,"percentageDem1980":14.1,"percentageDem1984":16.9,"percentageDem1988":21,"percentageDem1992":13,"percentageDem1996":18.7,"percentageDem2000":13.7,"percentageDem2004":11.6,"percentageDem2008":18.8,"percentageRep1980":83.4,"percentageRep1984":82.6,"percentageRep1988":77.2,"percentageRep1992":56.8,"percentageRep1996":71.1,"percentageRep2000":81.7,"percentageRep2004":86,"percentageRep2008":77.7,"whitePopulation":516176,"blackPopulation":4320,"americanIndianAndAlaskanNativePopulation":4063,"asianPopulation":7926,"nativeHawaiianAndPacificIslanderPopulation":3417,"twoOrMoreRacesPopulation":9405,"hispanicOrLatinoPopulation":53764,"normalizedName":"utah-ut"}