{"reducedName":"warren,mo","lowercaseName":"warren, mo","areaname":"Warren, MO","stateCounty":29219,"totalPopulation":1389,"populationUnder18":7967,"populationOver65":13.7,"familiesBelowPovertyLevel":760,"medianFamilyIncome":62480,"meanFamilyIncome":71522,"incomeLessThan10K":342,"incomeBtw10And15K":318,"incomeBtw15And20K":299,"incomeBtw20And25K":240,"incomeBtw25And30K":317,"incomeBtw30And35K":525,"incomeBtw35And40K":386,"incomeBtw40And45K":441,"incomeBtw45And50K":490,"incomeBtw50And60K":716,"incomeBtw60And75K":1204,"incomeBtw75And100K":1631,"incomeBtw100And125K":711,"incomeBtw125And150K":430,"incomeBtw150And200K":238,"income200Plus":223,"unemploymentRate2009":11.3,"unemploymentRate2010":11,"percentageDem1980":31.6,"percentageDem1984":27.6,"percentageDem1988":39.6,"percentageDem1992":37.1,"percentageDem1996":40,"percentageDem2000":42.1,"percentageDem2004":40.7,"percentageDem2008":43,"percentageRep1980":64.7,"percentageRep1984":72.4,"percentageRep1988":60.1,"percentageRep1992":34.1,"percentageRep1996":43.8,"percentageRep2000":55.7,"percentageRep2004":58.7,"percentageRep2008":55.7,"whitePopulation":30117,"blackPopulation":817,"americanIndianAndAlaskanNativePopulation":135,"asianPopulation":83,"nativeHawaiianAndPacificIslanderPopulation":4,"twoOrMoreRacesPopulation":329,"hispanicOrLatinoPopulation":776,"normalizedName":"warren-mo"}